is_annotated/__init__.py
is_annotated/py.typed
is_annotated-1.0.1.dist-info/METADATA
is_annotated-1.0.1.dist-info/WHEEL
is_annotated-1.0.1.dist-info/licenses/LICENSE
is_annotated-1.0.1.dist-info/RECORD
