Metadata-Version: 2.3
Name: is_annotated
Version: 1.0.1
Summary: Check if an object is an `Annotated` type.
Project-URL: Bug Tracker, https://github.com/GalacticDynamics/is_annotated/issues
Project-URL: Changelog, https://github.com/GalacticDynamics/is_annotated/releases
Project-URL: Discussions, https://github.com/GalacticDynamics/is_annotated/discussions
Project-URL: Homepage, https://github.com/GalacticDynamics/is_annotated
Author-email: Nathaniel Starkman <nstarman@users.noreply.github.com>
License: Copyright 2024 Nathaniel Starkman
License-File: LICENSE
Classifier: Development Status :: 5 - Production/Stable
Classifier: Intended Audience :: Developers
Classifier: Intended Audience :: Science/Research
Classifier: License :: OSI Approved :: MIT License
Classifier: Operating System :: OS Independent
Classifier: Programming Language :: Python
Classifier: Programming Language :: Python :: 3
Classifier: Programming Language :: Python :: 3 :: Only
Classifier: Programming Language :: Python :: 3.9
Classifier: Programming Language :: Python :: 3.10
Classifier: Programming Language :: Python :: 3.11
Classifier: Programming Language :: Python :: 3.12
Classifier: Topic :: Scientific/Engineering
Classifier: Typing :: Typed
Requires-Python: >=3.9
Requires-Dist: typing-extensions>=4.0
Provides-Extra: dev
Requires-Dist: pytest-cov>=3; extra == 'dev'
Requires-Dist: pytest-github-actions-annotate-failures; extra == 'dev'
Requires-Dist: pytest>=6; extra == 'dev'
Requires-Dist: sybil; extra == 'dev'
Provides-Extra: test
Requires-Dist: pytest-cov>=3; extra == 'test'
Requires-Dist: pytest-github-actions-annotate-failures; extra == 'test'
Requires-Dist: pytest>=6; extra == 'test'
Requires-Dist: sybil; extra == 'test'
